MetaPreprocessor/__init__.py
metapreprocessor-0.0.5.dist-info/METADATA
metapreprocessor-0.0.5.dist-info/WHEEL
metapreprocessor-0.0.5.dist-info/licenses/LICENSE.md
metapreprocessor-0.0.5.dist-info/RECORD
