Metadata-Version: 2.4
Name: MetaPreprocessor
Version: 0.0.5
Summary: Generate C code using Python code embedded within C source files.
Author-email: "Phuc X. Doan" <phucxdoan@gmail.com>
License-Expression: MIT
License-File: LICENSE.md
Requires-Python: >=3.13
